{"total":21,"pageSize":10,"pageCount":3,"data":[{"title":"執蘖","slug":"zhinie","date":"2012-06-08T14:40:18.000Z","updated":"2020-06-15T17:17:04.566Z","comments":true,"path":"api/articles/zhinie.json","excerpt":"蘖，树木被砍去或倒下后长出的新芽。男孩呆呆地盯着电脑屏幕，第二次看着百度百科对这个字所做出的解释。结果可想而知，和第一次的一模一样，但现在的他，已不再是当初那个傻傻坚持的男孩。","keywords":null,"cover":"https://suyan.peng-ming.cn/cover/zhinie.jpg","content":null,"raw":null,"categories":[{"name":"daily","path":"api/categories/daily.json"}],"tags":[{"name":"article","path":"api/tags/article.json"}]}]}