[{"name":"Android","path":"api/tags/Android.json","count":16},{"name":"source code","path":"api/tags/source code.json","count":5},{"name":"AOP","path":"api/tags/AOP.json","count":2},{"name":"optimization","path":"api/tags/optimization.json","count":1},{"name":"AspectJ","path":"api/tags/AspectJ.json","count":1},{"name":"library","path":"api/tags/library.json","count":7},{"name":"MVVM","path":"api/tags/MVVM.json","count":1},{"name":"Design pattern","path":"api/tags/Design pattern.json","count":1}]